benchflow/BaseAgent.py
benchflow/BaseBench.py
benchflow/Bench.py
benchflow/BenchClient.py
benchflow/__init__.py
benchflow/load_benchmark.py
benchflow/agents/__init__.py
benchflow/agents/bird_openai.py
benchflow/agents/crag_openai.py
benchflow/agents/mmlu_openai.py
benchflow/agents/rarebench_openai.py
benchflow/agents/swebench_sweagent.py
benchflow/agents/webarena_langbase.py
benchflow/agents/webarena_openai.py
benchflow/agents/webcanvas_langbase.py
benchflow/agents/webcanvas_openai.py
benchflow/benchmarks/__init__.py
benchflow/benchmarks/crag.py
benchflow/benchmarks/mmlupro.py
benchflow/benchmarks/swebench.py
benchflow/benchmarks/webarena.py
benchflow/benchmarks/webcanvas.py
benchflow/schemas/BenchArgs.py
benchflow/schemas/BenchmarkResults.py
benchflow/schemas/InputData.py
benchflow/schemas/__init__.py
benchflow-0.1.13.dist-info/METADATA
benchflow-0.1.13.dist-info/WHEEL
benchflow-0.1.13.dist-info/licenses/LICENSE
benchflow-0.1.13.dist-info/RECORD
