Metadata-Version: 2.4
Name: benchflow
Version: 0.1.13
Summary: A tool for easy benchmarking.
Project-URL: Homepage, https://github.com/benchflow-ai/benchflow
Project-URL: Bug Tracker, https://github.com/benchflow-ai/benchflow/issues
Author-email: Hongji Xu <kirk@benchflow.ai>, Xiangyi Li <xiangyi@benchflow.ai>
Maintainer-email: Hongji Xu <kirk@benchflow.ai>, Xiangyi Li <xiangyi@benchflow.ai>
License: MIT
License-File: LICENSE
Classifier: License :: OSI Approved :: MIT License
Classifier: Operating System :: OS Independent
Classifier: Programming Language :: Python :: 3
Requires-Python: >=3.10
Requires-Dist: datasets>=2.0.0
Requires-Dist: docker>=6.0.0
Requires-Dist: fastapi>=0.100.0
Requires-Dist: jinja2>=3.1.6
Requires-Dist: json5>=0.9.15
Requires-Dist: openai>=1.0.0
Requires-Dist: pytest>=8.3.5
Requires-Dist: requests>=2.30.0
Requires-Dist: ruff>=0.7.0
Requires-Dist: uvicorn>=0.24.0
